adafruit_htu21d.py
adafruit_circuitpython_htu21d-0.11.20.dist-info/licenses/LICENSE
adafruit_circuitpython_htu21d-0.11.20.dist-info/METADATA
adafruit_circuitpython_htu21d-0.11.20.dist-info/WHEEL
adafruit_circuitpython_htu21d-0.11.20.dist-info/top_level.txt
adafruit_circuitpython_htu21d-0.11.20.dist-info/RECORD
